{
    "uuid": "09bb40c4-906a-4ad1-b065-296f6e0fc31a",
    "title": "Why aren’t palindromes named semordromes?",
    "topic": "Recursion",
    "tags": ["Liaoqitian", "python indexing", "beta", "final", "dead python", "hard", "summative"],
    "type": "v3",
    "singleVariant": true,
    "gradingMethod": "External",
    "externalGradingOptions": {
        "enabled": true,
        "image": "prairielearn/grader-python",
        "entrypoint": "/python_autograder/run.sh",
        "timeout": 20
    }
}